sprauta/__about__.py
sprauta/__init__.py
sprauta/py.typed
sprauta/sprauta.py
sprauta-0.2.1.dist-info/METADATA
sprauta-0.2.1.dist-info/WHEEL
sprauta-0.2.1.dist-info/RECORD
