Metadata-Version: 2.1
Name: sprauta
Version: 0.2.1
Project-URL: Documentation, https://github.com/saevarorn/sprauta#readme
Project-URL: Issues, https://github.com/saevarorn/sprauta/issues
Project-URL: Source, https://github.com/saevarorn/sprauta
Author-email: Sævar Örn Kjartansson <saevar90@gmail.com>
License-Expression: MIT
Classifier: Development Status :: 4 - Beta
Classifier: Programming Language :: Python
Classifier: Programming Language :: Python :: 3.8
Classifier: Programming Language :: Python :: 3.9
Classifier: Programming Language :: Python :: 3.10
Classifier: Programming Language :: Python :: 3.11
Classifier: Programming Language :: Python :: 3.12
Classifier: Programming Language :: Python :: Implementation :: CPython
Classifier: Programming Language :: Python :: Implementation :: PyPy
Requires-Python: >=3.8
Requires-Dist: typing-extensions>=4.7.1
